qmlt/__init__.py
qmlt/_version.py
qmlt/helpers.py
qmlt/numerical/__init__.py
qmlt/numerical/helpers.py
qmlt/numerical/learner.py
qmlt/numerical/losses.py
qmlt/numerical/plot.py
qmlt/numerical/regularizers.py
qmlt/tf/__init__.py
qmlt/tf/helpers.py
qmlt/tf/learner.py
qmlt/tf/losses.py
qmlt-0.7.1.dist-info/DESCRIPTION.rst
qmlt-0.7.1.dist-info/METADATA
qmlt-0.7.1.dist-info/RECORD
qmlt-0.7.1.dist-info/WHEEL
qmlt-0.7.1.dist-info/metadata.json
qmlt-0.7.1.dist-info/top_level.txt
