Metadata-Version: 2.0
Name: qmlt
Version: 0.7.1
Summary: Machine learning and optimization of quantum optical circuits
Home-page: http://xanadu.ai
Author: Xanadu Inc.
Author-email: maria@xanadu.ai
License: LICENSE
Platform: UNKNOWN
Classifier: Development Status :: 3 - Alpha
Classifier: Environment :: Console
Classifier: Intended Audience :: Science/Research
Classifier: License :: OSI Approved :: Apache Software License
Classifier: Natural Language :: English
Classifier: Operating System :: POSIX
Classifier: Operating System :: MacOS :: MacOS X
Classifier: Operating System :: POSIX :: Linux
Classifier: Operating System :: Microsoft :: Windows
Classifier: Programming Language :: Python
Classifier: Programming Language :: Python :: 3
Classifier: Programming Language :: Python :: 3.5
Classifier: Programming Language :: Python :: 3.6
Classifier: Programming Language :: Python :: 3 :: Only
Classifier: Topic :: Scientific/Engineering :: Physics
Provides: qmlt
Requires-Dist: scikit-learn (>=0.19)
Requires-Dist: matplotlib (>=2.0)
Requires-Dist: strawberryfields (>=0.7.3)
